{"stats":{"minecraft:used":{"minecraft:oak_log":3,"minecraft:dirt":4,"minecraft:lime_concrete":9,"minecraft:grass_block":1},"minecraft:mined":{"minecraft:grass_block":4,"minecraft:dirt":2},"minecraft:dropped":{"minecraft:dirt":1},"minecraft:picked_up":{"minecraft:lime_concrete":64,"minecraft:grass_block":1,"minecraft:dirt":5,"minecraft:paper":94},"minecraft:custom":{"minecraft:time_since_rest":2334838,"minecraft:open_chest":60,"minecraft:crouch_one_cm":3736,"minecraft:play_time":2334838,"minecraft:sprint_one_cm":40408,"minecraft:damage_taken":20,"minecraft:walk_one_cm":150680,"minecraft:sneak_time":1035,"minecraft:drop":1,"minecraft:jump":219,"minecraft:leave_game":18,"minecraft:time_since_death":2334838,"minecraft:total_world_time":2334838,"minecraft:fall_one_cm":4863,"minecraft:fly_one_cm":29432}},"DataVersion":3218}